nautobot_uuid_lookup/__init__.py
nautobot_uuid_lookup/api/urls.py
nautobot_uuid_lookup/api/views.py
nautobot_uuid_lookup/migrations/__init__.py
nautobot_uuid_lookup/models.py
nautobot_uuid_lookup/tests/__init__.py
nautobot_uuid_lookup/tests/test_models.py
nautobot_uuid_lookup/tests/test_views.py
nautobot_uuid_lookup/urls.py
nautobot_uuid_lookup/views.py
nautobot_uuid_lookup-1.0.0.dist-info/LICENSE.txt
nautobot_uuid_lookup-1.0.0.dist-info/METADATA
nautobot_uuid_lookup-1.0.0.dist-info/WHEEL
nautobot_uuid_lookup-1.0.0.dist-info/RECORD
